calmjs/parse/__init__.py
calmjs/parse/asttypes.py
calmjs/parse/exceptions.py
calmjs/parse/factory.py
calmjs/parse/io.py
calmjs/parse/rules.py
calmjs/parse/ruletypes.py
calmjs/parse/sourcemap.py
calmjs/parse/unicode_chars.py
calmjs/parse/utils.py
calmjs/parse/vlq.py
calmjs/parse/walkers.py
calmjs/parse/handlers/__init__.py
calmjs/parse/handlers/core.py
calmjs/parse/handlers/indentation.py
calmjs/parse/handlers/obfuscation.py
calmjs/parse/lexers/__init__.py
calmjs/parse/lexers/es5.py
calmjs/parse/lexers/tokens.py
calmjs/parse/parsers/__init__.py
calmjs/parse/parsers/es5.py
calmjs/parse/parsers/lextab_es5_py3_ply3_10.py
calmjs/parse/parsers/lextab_es5_py3_ply3_11.py
calmjs/parse/parsers/lextab_es5_py3_ply3_6.py
calmjs/parse/parsers/lextab_es5_py3_ply3_8.py
calmjs/parse/parsers/lextab_es5_py3_ply3_9.py
calmjs/parse/parsers/optimize.py
calmjs/parse/parsers/yacctab_es5_py3_ply3_10.py
calmjs/parse/parsers/yacctab_es5_py3_ply3_11.py
calmjs/parse/parsers/yacctab_es5_py3_ply3_6.py
calmjs/parse/parsers/yacctab_es5_py3_ply3_8.py
calmjs/parse/parsers/yacctab_es5_py3_ply3_9.py
calmjs/parse/testing/__init__.py
calmjs/parse/testing/util.py
calmjs/parse/tests/__init__.py
calmjs/parse/tests/lexer.py
calmjs/parse/tests/parser.py
calmjs/parse/tests/test_asttypes.py
calmjs/parse/tests/test_es5_lexer.py
calmjs/parse/tests/test_es5_parser.py
calmjs/parse/tests/test_es5_unparser.py
calmjs/parse/tests/test_factory.py
calmjs/parse/tests/test_handlers_indentation.py
calmjs/parse/tests/test_handlers_obfuscation.py
calmjs/parse/tests/test_handlers_simple.py
calmjs/parse/tests/test_io.py
calmjs/parse/tests/test_parsers_optimize.py
calmjs/parse/tests/test_pptypes.py
calmjs/parse/tests/test_rules.py
calmjs/parse/tests/test_ruletypes.py
calmjs/parse/tests/test_sourcemap.py
calmjs/parse/tests/test_testing.py
calmjs/parse/tests/test_unparsers_base.py
calmjs/parse/tests/test_unparsers_extractor.py
calmjs/parse/tests/test_unparsers_walker.py
calmjs/parse/tests/test_utils.py
calmjs.parse-1.3.2.dist-info/LICENSE
calmjs.parse-1.3.2.dist-info/METADATA
calmjs.parse-1.3.2.dist-info/WHEEL
calmjs.parse-1.3.2.dist-info/top_level.txt
calmjs.parse-1.3.2.dist-info/RECORD
