Metadata-Version: 2.1
Name: calmjs.parse
Version: 1.3.2
Summary: Various parsers for ECMA standards.
Home-page: https://github.com/calmjs/calmjs.parse
Author: Tommy Yu
Author-email: tommy.yu@auckland.ac.nz
License: mit
Classifier: Development Status :: 5 - Production/Stable
Classifier: Intended Audience :: Developers
Classifier: License :: OSI Approved :: MIT License
Classifier: Operating System :: OS Independent
Classifier: Programming Language :: JavaScript
Classifier: Programming Language :: Python :: 3.3
Classifier: Programming Language :: Python :: 3.4
Classifier: Programming Language :: Python :: 3.5
Classifier: Programming Language :: Python :: 3.6
Classifier: Programming Language :: Python :: 3.7
Classifier: Programming Language :: Python :: 3.8
Classifier: Programming Language :: Python :: 3.9
Classifier: Programming Language :: Python :: 3.10
Classifier: Programming Language :: Python :: 3.11
Classifier: Programming Language :: Python :: 3.12
Classifier: Programming Language :: Python :: 3.13
Requires-Python: >=3.3
License-File: LICENSE
Requires-Dist: setuptools
Requires-Dist: ply >=3.6
